{
    "unid": "ca0259",
    "isAlias": true,
    "basic": {
        "name": "日值神",
        "pinyin": "ri_zhi_shen",
        "aliases": [
            "日值守神",
            "日值护神",
            "日值当班神"
        ],
        "type": "character_alias",
        "category": "alias"
    },
    "attributes": {
        "level": {
            "id": "gong_cao",
            "name": "功曹",
            "tier": 5,
            "category": "celestial"
        },
        "rank": 100,
        "power": 73,
        "influence": 76,
        "morality": "lawful_neutral"
    },
    "metadata": {
        "description": "日值功曹的值守神称谓，强调其作为日常值班守护神的职责地位。这个称谓体现了日值功曹在天庭值班体系中的重要作用，负责日常时间的值守和管理工作。",
        "tags": [
            "time_deity",
            "four_duty_officers",
            "duty_guardian",
            "temporal_authority",
            "celestial_bureaucracy",
            "daily_guardian",
            "duty_rotation",
            "time_management"
        ],
        "sourceChapters": [
            7,
            8
        ],
        "firstAppearance": 7,
        "significance": "体现了日值功曹作为日常值班守护神的职责地位和管理权威",
        "culturalBackground": "日值神是道教天庭值班体系的重要组成部分，值神概念体现了天庭严密的值班制度，日值神专门负责日常时间的值守和管理，确保日常时间秩序的正常运行",
        "lastUpdated": "2025-01-08T00:00:00Z",
        "originalCharacter": "c0100"
    }
}
