{
    "unid": "c0005",
    "isAlias": false,
    "basic": {
        "name": "白龙马",
        "pinyin": "bai_long_ma",
        "aliases": [
            "西海龙王三太子敖烈",
            "小白龙",
            "龙马",
            "白马",
            "八部天龙",
            "敖烈",
            "三太子"
        ],
        "type": "character",
        "category": "protagonist"
    },
    "attributes": {
        "level": {
            "id": "xi_hai_san_tai_zi",
            "name": "西海三太子",
            "tier": 6,
            "category": "divine"
        },
        "rank": 5,
        "power": 70,
        "influence": 40,
        "morality": "lawful_good"
    },
    "metadata": {
        "description": "西海龙王三太子敖烈，因纵火烧了殿上明珠被贬，后化作白马载师取经。拥有龙族血统，能在关键时刻恢复龙身作战。",
        "tags": [
            "protagonist",
            "dragon",
            "horse",
            "shapeshifter",
            "loyal",
            "mount",
            "royal_blood",
            "fire_breather",
            "noble",
            "transformed"
        ],
        "sourceChapters": [
            15, 16, 17, 18, 19, 20,
            21, 22, 23, 24, 25, 26, 27, 28, 29, 30, 31, 32, 33, 34, 35, 36, 37, 38, 39, 40,
            41, 42, 43, 44, 45, 46, 47, 48, 49, 50, 51, 52, 53, 54, 55, 56, 57, 58, 59, 60,
            61, 62, 63, 64, 65, 66, 67, 68, 69, 70, 71, 72, 73, 74, 75, 76, 77, 78, 79, 80,
            81, 82, 83, 84, 85, 86, 87, 88, 89, 90, 91, 92, 93, 94, 95, 96, 97, 98, 99, 100
        ],
        "firstAppearance": 15,
        "lastUpdated": "2025-01-08T00:00:00Z"
    }
}
