{
    "unid": "ca0017",
    "isAlias": true,
    "basic": {
        "name": "金蝉子",
        "pinyin": "jin_chan_zi",
        "aliases": [
            "金蝉长老",
            "二弟子",
            "如来二弟子"
        ],
        "type": "character_alias",
        "category": "alias"
    },
    "attributes": {
        "level": {
            "id": "fo_zu",
            "name": "佛祖",
            "tier": 9,
            "category": "buddha"
        },
        "rank": 2,
        "power": 85,
        "influence": 95,
        "morality": "lawful_good"
    },
    "metadata": {
        "description": "唐僧的前世身份，如来佛祖的二弟子，因轻慢佛法被贬下凡间转世。",
        "tags": [
            "alias",
            "previous_life",
            "buddha_disciple",
            "reincarnation",
            "golden_cicada"
        ],
        "sourceChapters": [
            8, 9, 10, 11, 12, 98, 99, 100
        ],
        "firstAppearance": 8,
        "lastUpdated": "2025-01-08T00:00:00Z",
        "originalCharacter": "c0002"
    }
}
